cldr_language_helpers/__init__.py
cldr_language_helpers/alphabets.py
cldr_language_helpers/annotator.py
cldr_language_helpers/conf.py
cldr_language_helpers/utils.py
cldr_language_helpers/data/language_alphabets.json
cldr_language_helpers/data/language_alphabets_compressed.json
cldr_language_helpers/data/languages.json
cldr_language_helpers/data/uchar_to_lang_map.json
cldr_language_helpers-1.2.0.dist-info/METADATA
cldr_language_helpers-1.2.0.dist-info/WHEEL
cldr_language_helpers-1.2.0.dist-info/top_level.txt
cldr_language_helpers-1.2.0.dist-info/RECORD
