Metadata-Version: 2.1
Name: cldr-language-helpers
Version: 1.2.0
Summary: Some helpful unicode string processing tools in native Python
Home-page: https://github.com/night-crawler/cldr-language-helpers
Author: night-crawler
Author-email: lilo.panic@gmail.com
License: MIT
Platform: UNKNOWN
Classifier: Environment :: Web Environment
Classifier: Intended Audience :: Developers
Classifier: Operating System :: OS Independent
Classifier: Programming Language :: Python
Classifier: Programming Language :: Python :: 3
Classifier: Programming Language :: Python :: 3.6
Classifier: Programming Language :: Python :: 3.7
Classifier: License :: OSI Approved :: MIT License
Requires-Python: >=3.6
Requires-Dist: funcy
